docs/_scripts/gen_api_pages.py
splitgill/__init__.py
splitgill/diffing.py
splitgill/ingest.py
splitgill/locking.py
splitgill/manager.py
splitgill/model.py
splitgill/search.py
splitgill/utils.py
splitgill/indexing/__init__.py
splitgill/indexing/fields.py
splitgill/indexing/geo.py
splitgill/indexing/index.py
splitgill/indexing/options.py
splitgill/indexing/parser.py
splitgill/indexing/syncing.py
splitgill/indexing/templates.py
splitgill-3.2.2.dist-info/licenses/LICENSE
tests/indexing/__init__.py
tests/indexing/test_fields.py
tests/indexing/test_geo.py
tests/indexing/test_index.py
tests/indexing/test_options.py
tests/indexing/test_parser.py
tests/indexing/test_templates.py
splitgill-3.2.2.dist-info/METADATA
splitgill-3.2.2.dist-info/WHEEL
splitgill-3.2.2.dist-info/top_level.txt
splitgill-3.2.2.dist-info/RECORD
