Metadata-Version: 2.4
Name: splitgill
Version: 3.2.2
Summary: Versioned search library
Author-email: Natural History Museum <data@nhm.ac.uk>
License: GPL-3.0-or-later
Project-URL: repository, https://github.com/NaturalHistoryMuseum/splitgill
Project-URL: changelog, https://github.com/NaturalHistoryMuseum/splitgill/blob/main/CHANGELOG.md
Classifier: Development Status :: 5 - Production/Stable
Classifier: License :: OSI Approved :: GNU General Public License v3 (GPLv3)
Classifier: Programming Language :: Python
Classifier: Programming Language :: Python :: 3 :: Only
Classifier: Programming Language :: Python :: 3.8
Classifier: Programming Language :: Python :: 3.9
Classifier: Programming Language :: Python :: 3.10
Classifier: Programming Language :: Python :: 3.11
Requires-Python: >=3.8
License-File: LICENSE
Requires-Dist: elasticsearch[async]>=8.0.0
Requires-Dist: elasticsearch-dsl>=8.13.1
Requires-Dist: pymongo>=4.4.1
Requires-Dist: cytoolz>=0.12.3
Requires-Dist: fastnumbers>=5.0.1
Requires-Dist: pyproj>=3.5.0
Requires-Dist: shapely>=2.0.5
Requires-Dist: regex>=2024.7.24
Requires-Dist: orjson>=3.10.6
Requires-Dist: StrEnum>=0.4.15
Provides-Extra: test
Requires-Dist: mock; extra == "test"
Requires-Dist: pytest; extra == "test"
Requires-Dist: pytest-cov; extra == "test"
Requires-Dist: coveralls; extra == "test"
Requires-Dist: freezegun; extra == "test"
Requires-Dist: pytest-asyncio; extra == "test"
Provides-Extra: docs
Requires-Dist: mkdocs; extra == "docs"
Requires-Dist: mkdocstrings[python]; extra == "docs"
Requires-Dist: mkdocs-material; extra == "docs"
Requires-Dist: mkdocs-gen-files; extra == "docs"
Requires-Dist: mkdocs-section-index; extra == "docs"
Requires-Dist: mkdocs-include-markdown-plugin; extra == "docs"
Dynamic: license-file
